{
  "formatVersion": 1,
  "database": {
    "version": 3,
    "identityHash": "be7b379e86c8eb2e4acd99cd436f819a",
    "entities": [
      {
        "tableName": "CardEntity",
        "createSql": "CREATE TABLE IF NOT EXISTS `${TABLE_NAME}` (`id` TEXT NOT NULL, `dbfid` TEXT, `name` TEXT, `text` TEXT, `flavor` TEXT, `artist` TEXT, `attack` TEXT, `cardClass` TEXT, `collectible` TEXT, `cost` TEXT, `elite` TEXT, `faction` TEXT, `health` TEXT, `mechanics` TEXT, `rarity` TEXT, `set` TEXT, `type` TEXT, PRIMARY KEY(`id`))",
        "fields": [
          {
            "fieldPath": "id",
            "columnName": "id",
            "affinity": "TEXT",
            "notNull": true
          },
          {
            "fieldPath": "dbfid",
            "columnName": "dbfid",
            "affinity": "TEXT",
            "notNull": false
          },
          {
            "fieldPath": "name",
            "columnName": "name",
            "affinity": "TEXT",
            "notNull": false
          },
          {
            "fieldPath": "text",
            "columnName": "text",
            "affinity": "TEXT",
            "notNull": false
          },
          {
            "fieldPath": "flavor",
            "columnName": "flavor",
            "affinity": "TEXT",
            "notNull": false
          },
          {
            "fieldPath": "artist",
            "columnName": "artist",
            "affinity": "TEXT",
            "notNull": false
          },
          {
            "fieldPath": "attack",
            "columnName": "attack",
            "affinity": "TEXT",
            "notNull": false
          },
          {
            "fieldPath": "cardClass",
            "columnName": "cardClass",
            "affinity": "TEXT",
            "notNull": false
          },
          {
            "fieldPath": "collectible",
            "columnName": "collectible",
            "affinity": "TEXT",
            "notNull": false
          },
          {
            "fieldPath": "cost",
            "columnName": "cost",
            "affinity": "TEXT",
            "notNull": false
          },
          {
            "fieldPath": "elite",
            "columnName": "elite",
            "affinity": "TEXT",
            "notNull": false
          },
          {
            "fieldPath": "faction",
            "columnName": "faction",
            "affinity": "TEXT",
            "notNull": false
          },
          {
            "fieldPath": "health",
            "columnName": "health",
            "affinity": "TEXT",
            "notNull": false
          },
          {
            "fieldPath": "mechanics",
            "columnName": "mechanics",
            "affinity": "TEXT",
            "notNull": false
          },
          {
            "fieldPath": "rarity",
            "columnName": "rarity",
            "affinity": "TEXT",
            "notNull": false
          },
          {
            "fieldPath": "set",
            "columnName": "set",
            "affinity": "TEXT",
            "notNull": false
          },
          {
            "fieldPath": "type",
            "columnName": "type",
            "affinity": "TEXT",
            "notNull": false
          }
        ],
        "primaryKey": {
          "columnNames": [
            "id"
          ],
          "autoGenerate": false
        },
        "indices": [],
        "foreignKeys": []
      }
    ],
    "setupQueries": [
      "CREATE TABLE IF NOT EXISTS room_master_table (id INTEGER PRIMARY KEY,identity_hash TEXT)",
      "INSERT OR REPLACE INTO room_master_table (id,identity_hash) VALUES(42, \"be7b379e86c8eb2e4acd99cd436f819a\")"
    ]
  }
}